[
  {
    "id": "TD01",
    "description": "test",
    "type": "test",
    "preConditions": "test",
    "steps": [
      "test"
    ],
    "expectedResults": "tes",
    "actualResults": "tes",
    "status": "tes",
    "comments": "tes"
  },
  {
    "id": "TD02",
    "description": "test 2",
    "type": "test 2",
    "preConditions": "test 2",
    "steps": [
      "test 2"
    ],
    "expectedResults": "test 2",
    "actualResults": "test 2",
    "status": "test 2",
    "comments": "test 2"
  }
]